CHANGES.rst
MANIFEST.in
README.rst
setup.py
src/apptrace/__init__.py
src/apptrace/code.html
src/apptrace/index.html
src/apptrace/instruments.py
src/apptrace/middleware.py
src/apptrace/overview.py
src/apptrace.egg-info/PKG-INFO
src/apptrace.egg-info/SOURCES.txt
src/apptrace.egg-info/dependency_links.txt
src/apptrace.egg-info/entry_points.txt
src/apptrace.egg-info/not-zip-safe
src/apptrace.egg-info/requires.txt
src/apptrace.egg-info/top_level.txt
src/apptrace/scripts/__init__.py
src/apptrace/scripts/apptracectl.py
src/apptrace/static/apptrace.css
src/apptrace/static/apptrace.js
src/apptrace/static/jquery-1.4.2.min.js
src/apptrace/static/flot/API.txt
src/apptrace/static/flot/FAQ.txt
src/apptrace/static/flot/LICENSE.txt
src/apptrace/static/flot/Makefile
src/apptrace/static/flot/NEWS.txt
src/apptrace/static/flot/PLUGINS.txt
src/apptrace/static/flot/README.txt
src/apptrace/static/flot/excanvas.js
src/apptrace/static/flot/excanvas.min.js
src/apptrace/static/flot/jquery.colorhelpers.js
src/apptrace/static/flot/jquery.colorhelpers.min.js
src/apptrace/static/flot/jquery.flot.crosshair.js
src/apptrace/static/flot/jquery.flot.crosshair.min.js
src/apptrace/static/flot/jquery.flot.image.js
src/apptrace/static/flot/jquery.flot.image.min.js
src/apptrace/static/flot/jquery.flot.js
src/apptrace/static/flot/jquery.flot.min.js
src/apptrace/static/flot/jquery.flot.navigate.js
src/apptrace/static/flot/jquery.flot.navigate.min.js
src/apptrace/static/flot/jquery.flot.selection.js
src/apptrace/static/flot/jquery.flot.selection.min.js
src/apptrace/static/flot/jquery.flot.stack.js
src/apptrace/static/flot/jquery.flot.stack.min.js
src/apptrace/static/flot/jquery.flot.threshold.js
src/apptrace/static/flot/jquery.flot.threshold.min.js
src/apptrace/static/flot/jquery.js
src/apptrace/static/flot/jquery.min.js
src/apptrace/static/flot/examples/ajax.html
src/apptrace/static/flot/examples/annotating.html
src/apptrace/static/flot/examples/arrow-down.gif
src/apptrace/static/flot/examples/arrow-left.gif
src/apptrace/static/flot/examples/arrow-right.gif
src/apptrace/static/flot/examples/arrow-up.gif
src/apptrace/static/flot/examples/basic.html
src/apptrace/static/flot/examples/data-eu-gdp-growth-1.json
