Metadata-Version: 1.0
Name: apptrace
Version: 0.2.3
Summary: WSGI middleware to measure the memory footprint of GAE Python applications.
Home-page: http://code.google.com/p/apptrace
Author: Tobias Rodaebel
Author-email: tobias.rodaebel@googlemail.com
License: Apache License 2.0
Keywords: google app engine gae heapy guppy
Platform: UNKNOWN
Classifier: Development Status :: 4 - Beta
Classifier: Environment :: Web Environment
Classifier: Intended Audience :: Developers
Classifier: License :: OSI Approved :: Apache Software License
Classifier: Natural Language :: English
Classifier: Operating System :: OS Independent
Classifier: Programming Language :: Python
Classifier: Topic :: Internet :: WWW/HTTP
Classifier: Topic :: Internet :: WWW/HTTP :: WSGI :: Server
